{
  "date": "2026-07-14",
  "word": { "nl": "het ziekenfonds", "art": "het", "split": "ziek (doente) + fonds (fundo)", "pt": "o plano de saúde, a mutualidade (sistema belga de seguro de saúde)", "emoji": "🏥" },
  "phrase": {
    "nl": [{"t":"Ik","r":"pron"},{"t":"heb","r":"verb"},{"t":"gisteren","r":"adv"},{"t":"hard","r":"adv"},{"t":"gewerkt","r":"verb"},{"t":".","r":"punc"}],
    "pt": [{"t":"Eu","r":"pron"},{"t":"trabalhei","r":"verb"},{"t":"muito","r":"adv"},{"t":"ontem","r":"adv"},{"t":".","r":"punc"}],
    "lit": "eu heb (tenho) ontem duro gewerkt (trabalhado)",
    "note": "No perfeito composto, \"heb\" (auxiliar) fica na segunda posição da frase e o particípio \"gewerkt\" vai lá pro final, com os advérbios (gisteren, hard) no meio. Em português, o verbo \"trabalhei\" fica todo junto, sem essa separação."
  }
}
